ns/__init__.py
ns/demux/__init__.py
ns/demux/fib_demux.py
ns/demux/flow_demux.py
ns/demux/random_demux.py
ns/flow/__init__.py
ns/flow/bbr.py
ns/flow/cc.py
ns/flow/cubic.py
ns/flow/flow.py
ns/packet/__init__.py
ns/packet/bbr_generator.py
ns/packet/dist_generator.py
ns/packet/packet.py
ns/packet/proxy_generator.py
ns/packet/proxy_sink.py
ns/packet/rate_sample.py
ns/packet/sink.py
ns/packet/tcp_generator.py
ns/packet/tcp_sink.py
ns/packet/trace_generator.py
ns/port/__init__.py
ns/port/monitor.py
ns/port/port.py
ns/port/red_port.py
ns/port/wire.py
ns/scheduler/__init__.py
ns/scheduler/drr.py
ns/scheduler/monitor.py
ns/scheduler/sp.py
ns/scheduler/virtual_clock.py
ns/scheduler/wfq.py
ns/shaper/__init__.py
ns/shaper/token_bucket.py
ns/shaper/two_rate_token_bucket.py
ns/switch/__init__.py
ns/switch/switch.py
ns/topos/__init__.py
ns/topos/fattree.py
ns/topos/utils.py
ns/topos/internet_topo_zoo/Aarnet.gml
ns/topos/internet_topo_zoo/Aarnet.graphml
ns/topos/internet_topo_zoo/Abilene.gml
ns/topos/internet_topo_zoo/Abilene.graphml
ns/topos/internet_topo_zoo/Abvt.gml
ns/topos/internet_topo_zoo/Abvt.graphml
ns/topos/internet_topo_zoo/Aconet.gml
ns/topos/internet_topo_zoo/Aconet.graphml
ns/topos/internet_topo_zoo/Agis.gml
ns/topos/internet_topo_zoo/Agis.graphml
ns/topos/internet_topo_zoo/Ai3.gml
ns/topos/internet_topo_zoo/Ai3.graphml
ns/topos/internet_topo_zoo/Airtel.gml
ns/topos/internet_topo_zoo/Airtel.graphml
ns/topos/internet_topo_zoo/Amres.gml
ns/topos/internet_topo_zoo/Amres.graphml
ns/topos/internet_topo_zoo/Ans.gml
ns/topos/internet_topo_zoo/Ans.graphml
ns/topos/internet_topo_zoo/Arn.gml
ns/topos/internet_topo_zoo/Arn.graphml
ns/topos/internet_topo_zoo/Arnes.gml
ns/topos/internet_topo_zoo/Arnes.graphml
ns/topos/internet_topo_zoo/Arpanet196912.gml
ns/topos/internet_topo_zoo/Arpanet196912.graphml
ns/topos/internet_topo_zoo/Arpanet19706.gml
ns/topos/internet_topo_zoo/Arpanet19706.graphml
ns/topos/internet_topo_zoo/Arpanet19719.gml
ns_py-0.4.4.dist-info/METADATA
ns_py-0.4.4.dist-info/WHEEL
ns_py-0.4.4.dist-info/licenses/LICENSE
ns_py-0.4.4.dist-info/RECORD
