Metadata-Version: 2.4
Name: ns.py
Version: 0.4.4
Summary: ns.py: a pythonic discrete-event network simulator
Project-URL: Homepage, https://github.com/TL-System/ns.py
Project-URL: Repository, https://github.com/TL-System/ns.py
Author: TL-System
License:                                  Apache License
License-File: LICENSE
Keywords: computer networking,discrete-event simulator
Classifier: Development Status :: 4 - Beta
Classifier: Intended Audience :: Developers
Classifier: Intended Audience :: Science/Research
Classifier: License :: OSI Approved :: Apache Software License
Classifier: Operating System :: OS Independent
Classifier: Programming Language :: Python :: 3
Classifier: Programming Language :: Python :: 3 :: Only
Classifier: Programming Language :: Python :: 3.13
Classifier: Topic :: Education
Classifier: Topic :: Scientific/Engineering
Classifier: Topic :: Software Development :: Libraries
Classifier: Topic :: Software Development :: Libraries :: Python Modules
Requires-Python: >=3.13
Requires-Dist: matplotlib
Requires-Dist: networkx
Requires-Dist: pyyaml
Requires-Dist: simpy
